srt_core/__init__.py
srt_core/config/__init__.py
srt_core/config/config.py
srt_core/utils/__init__.py
srt_core/utils/logger.py
srt_core-0.1.15.dist-info/LICENSE
srt_core-0.1.15.dist-info/METADATA
srt_core-0.1.15.dist-info/WHEEL
srt_core-0.1.15.dist-info/entry_points.txt
srt_core-0.1.15.dist-info/top_level.txt
srt_core-0.1.15.dist-info/RECORD
