Metadata-Version: 2.1
Name: srt-core
Version: 0.1.15
Summary: SolidRusT Core Libraries
Home-page: https://github.com/SolidRusT/srt-core
Author: Suparious
Author-email: suparious@solidrust.net
Classifier: Programming Language :: Python :: 3
Classifier: License :: OSI Approved :: MIT License
Classifier: Operating System :: OS Independent
Requires-Python: >=3.11
License-File: LICENSE
Requires-Dist: pyyaml
